pdcompare/__init__.py
pdcompare/compare.py
pdcompare/helper.py
pdcompare/index.py
pdcompare-0.1.6.dist-info/licenses/LICENSE
pdcompare-0.1.6.dist-info/METADATA
pdcompare-0.1.6.dist-info/WHEEL
pdcompare-0.1.6.dist-info/top_level.txt
pdcompare-0.1.6.dist-info/RECORD
