Metadata-Version: 2.4
Name: pdcompare
Version: 0.1.6
Summary: Used to compare 2 Pandas DFs
Home-page: https://github.com/jaceiverson/pandas-compare
Author: Jace Iverson
Author-email: iverson.jace@gmail.com
Project-URL: Bug Tracker, https://github.com/jaceiverson/pandas-compare
License-File: LICENSE
Dynamic: author
Dynamic: author-email
Dynamic: description
Dynamic: description-content-type
Dynamic: home-page
Dynamic: license-file
Dynamic: project-url
Dynamic: summary
